[
    "{\n    \"hotel_name\": \"Grand Mercure Guangzhou Baiyun International\\nAirport\",\n    \"hotel_address\": [\n        {\n            \"address_line_1\": \"No. 10 Konggang Avenue, Huadu District, Guangzhou, Guangdong, China\",\n            \"address_line_2\": null,\n            \"address_city\": \"Guangzhou\",\n            \"address_state\": \"Guangdong\",\n            \"address_zip_code\": null\n        }\n    ],\n    \"hotel_phone_no\": \"+86-20-86888418, +86-19128626784,+86-20-86888408\",\n    \"hotel_email\": null,\n    \"hotel_room_no\": \"1\",\n    \"hotel_room_type\": \"Comfortable King-size Bed Room\",\n    \"sur_name\": \"HASAN\",\n    \"given_name\": \"MOHAMMAD MOSABBERUL\",\n    \"address\": {\n        \"present_address\": [],\n        \"permanent_address\": []\n    },\n    \"check_in\": \"2025-12-25\",\n    \"check_out\": \"2025-12-27\",\n    \"occupancy\": \"2 guests\",\n    \"room_info\": \"1 queen bed\",\n    \"meal_plan\": \"No meals included\",\n    \"guest_details\": \"MOHAMMAD MOSABBERUL HASAN\",\n    \"no_of_pax\": [\n        {\n            \"type\": \"Adult\",\n            \"count\": \"2\"\n        },\n        {\n            \"type\": \"Child\",\n            \"count\": \"\"\n        },\n        {\n            \"type\": \"Infant\",\n            \"count\": \"\"\n        }\n    ],\n    \"booking_date\": null,\n    \"cancellation\": \"Free cancellation\",\n    \"terms_n_conditions\": \"If you fail to check in, a penalty equivalent to the cancellation\\nfee will be charged.\",\n    \"pcn\": null,\n    \"hcn\": \"1688894740348614\"\n}"
]